skipthoughts/__init__.py
skipthoughts/dropout.py
skipthoughts/gru.py
skipthoughts/skipthoughts.py
skipthoughts/version.py
skipthoughts-0.0.1.dist-info/LICENSE.txt
skipthoughts-0.0.1.dist-info/METADATA
skipthoughts-0.0.1.dist-info/WHEEL
skipthoughts-0.0.1.dist-info/top_level.txt
skipthoughts-0.0.1.dist-info/RECORD
