Metadata-Version: 2.1
Name: skipthoughts
Version: 0.0.1
Summary: Skipthoughts pretrained models for Pytorch
Home-page: https://github.com/cadene/skip-thoughts.torch
Author: Remi Cadene
Author-email: remi.cadene@icloud.com
License: UNKNOWN
Keywords: pytorch pretrained models skipthoughts deep learning
Platform: UNKNOWN
Classifier: Development Status :: 3 - Alpha
Classifier: Intended Audience :: Developers
Classifier: Topic :: Software Development :: Build Tools
Classifier: License :: OSI Approved :: MIT License
Classifier: Programming Language :: Python :: 3.6
Requires-Dist: torch
Requires-Dist: numpy
